inisync/__init__.py
inisync/__main__.py
inisync/inisync.py
inisync-1.1.dist-info/METADATA
inisync-1.1.dist-info/WHEEL
inisync-1.1.dist-info/entry_points.txt
inisync-1.1.dist-info/top_level.txt
inisync-1.1.dist-info/RECORD
