Metadata-Version: 2.1
Name: inisync
Version: 1.1
Summary: Sync value from one INI file to others
Home-page: UNKNOWN
Author: Constantin Gruber
Author-email: constantin.gruber@sixsentix.com
License: UNKNOWN
Platform: UNKNOWN
Requires-Python: >=3.6
